base69/__init__.py
base69/decoder.py
base69/encoder.py
encodelikepro-0.1.0.dist-info/METADATA
encodelikepro-0.1.0.dist-info/WHEEL
encodelikepro-0.1.0.dist-info/top_level.txt
encodelikepro-0.1.0.dist-info/RECORD
