Metadata-Version: 2.4
Name: encodelikepro
Version: 0.1.0
Summary: A Python package for base69 encoding
Author-email: Ahmed Tuzinac <tuzinac96@gmail.com>
Project-URL: Homepage, https://github.com/yourusername/base69
Project-URL: Issues, https://github.com/yourusername/base69/issues
Keywords: encoding,base69
Classifier: Programming Language :: Python :: 3
Classifier: License :: OSI Approved :: MIT License
Classifier: Operating System :: OS Independent
Requires-Python: >=3.7
